vbeam/__init__.py
vbeam/apodization/__init__.py
vbeam/apodization/combine.py
vbeam/apodization/mla.py
vbeam/apodization/no_apodization.py
vbeam/apodization/plane_wave.py
vbeam/apodization/plotting.py
vbeam/apodization/rtb.py
vbeam/apodization/tx_rx_apodization.py
vbeam/apodization/util.py
vbeam/apodization/window.py
vbeam/beamformers/__init__.py
vbeam/beamformers/building_blocks.py
vbeam/core/__init__.py
vbeam/core/apodization.py
vbeam/core/element_geometry.py
vbeam/core/interpolation.py
vbeam/core/kernel_data.py
vbeam/core/kernels.py
vbeam/core/speed_of_sound.py
vbeam/core/wave_data.py
vbeam/core/wavefront.py
vbeam/data_importers/__init__.py
vbeam/data_importers/pyuff_importer.py
vbeam/data_importers/setup.py
vbeam/experimental/beamformers/transformations.py
vbeam/fastmath/__init__.py
vbeam/fastmath/backend.py
vbeam/fastmath/traceable.py
vbeam/fastmath/included_backends/__init__.py
vbeam/fastmath/included_backends/jax_backend.py
vbeam/fastmath/included_backends/numpy_backend.py
vbeam/fastmath/included_backends/tensorflow_backend/__init__.py
vbeam/fastmath/included_backends/tensorflow_backend/vmap.py
vbeam/interpolation/__init__.py
vbeam/interpolation/fast_linear.py
vbeam/interpolation/nearest.py
vbeam/postprocess/__init__.py
vbeam/scan/__init__.py
vbeam/scan/base.py
vbeam/scan/linear_scan.py
vbeam/scan/sector_scan.py
vbeam/scan/util.py
vbeam/scan/advanced/__init__.py
vbeam/scan/advanced/apodization_filtered_scan.py
vbeam/scan/advanced/base.py
vbeam/scan/advanced/scan_converted_sector_scan.py
vbeam/speed_of_sound/__init__.py
vbeam/util/__init__.py
vbeam/util/_default_values.py
vbeam/util/_deprecations.py
vbeam/util/apply_windowed.py
vbeam/util/arrays.py
vbeam/util/coordinate_systems.py
vbeam/util/transformations.py
vbeam/util/vmap.py
vbeam/util/download/__init__.py
vbeam/util/geometry/__init__.py
vbeam/util/geometry/line.py
vbeam/util/geometry/v2.py
vbeam/util/jax/__init__.py
vbeam/util/jax/grad.py
vbeam/wavefront/__init__.py
vbeam/wavefront/focused.py
vbeam-1.0.10.dist-info/METADATA
vbeam-1.0.10.dist-info/WHEEL
vbeam-1.0.10.dist-info/licenses/LICENSE
vbeam-1.0.10.dist-info/RECORD
