Metadata-Version: 2.4
Name: vbeam
Version: 1.0.10
Summary: vbeam: a fast and differentiable beamformer
Project-URL: Homepage, https://github.com/magnusdk/vbeam/
Project-URL: Documentation, https://vbeam.readthedocs.io/en/latest/
Project-URL: Bug Tracker, https://github.com/magnusdk/vbeam/issues
Author-email: Magnus Dalen Kvalevåg <magnus.kvalevag@ntnu.no>
License-File: LICENSE
Classifier: License :: OSI Approved :: Apache Software License
Classifier: Operating System :: OS Independent
Classifier: Programming Language :: Python :: 3
Requires-Python: >=3.9
Requires-Dist: numpy
Requires-Dist: pyuff-ustb>=2.0.7
Requires-Dist: scipy
Requires-Dist: spekk>=1.0.6
Provides-Extra: backends
Requires-Dist: jax; extra == 'backends'
Requires-Dist: tensorflow; extra == 'backends'
Provides-Extra: test
Requires-Dist: hypothesis; extra == 'test'
Requires-Dist: pytest; extra == 'test'
